{
  "version": "1.0",
  "last_updated": "2025-01-27T22:30:00Z",
  "created_by": "Claude Sonnet 4 - Sonnet 4",
  "converted_from": "E:\\kos\\ai-Q\\agents\\blueprint\\standards\\enterprise_distribution_standards.yml",
  "conversion_timestamp": "2025-01-27T22:30:00Z",
  "converter": "RobustYAMLToJSONConverter v1.0",
  "purpose": "Converted from problematic YAML file: enterprise_distribution_standards.yml",
  "title": "Enterprise Distribution Standards",
  "original_content": "# Enterprise Distribution Standards\n# TOKEN COUNT: ~2,299 tokens\n---\nversion: \"1.0\"\nlast_updated: \"2025-07-03T00:00:00Z\"\npurpose: >\n  Defines enterprise-grade standards for distributing the AI-Q Knowledge Library System \n  across multiple organizations, environments, and deployment scenarios while maintaining \n  security, scalability, and maintainability.\n\n# CRITICAL POLICIES\ncritical_policies:\n  zero_technical_debt:\n    - \"No TODOs, temporary code, or manual steps allowed\"\n    - \"All code must be production-ready and fully tested\"\n    - \"No commented-out code or debug endpoints\"\n    - \"All changes must be versioned and immutable\"\n  \n  production_only_testing:\n    - \"All tests must use production data, services, and servers\"\n    - \"No development or test data allowed\"\n    - \"No mock services or simulated environments\"\n    - \"All test runs must be logged and auditable\"\n  \n  immutable_infrastructure:\n    - \"All infrastructure defined as code\"\n    - \"No manual infrastructure changes\"\n    - \"All environments must be identical\"\n    - \"Instant rollback capability required\"\n\n# FEATURE FLAG SYSTEM\nfeature_flags:\n  core_requirements:\n    - \"Zero hardcoded features - all configurable via flags\"\n    - \"Runtime toggle without code deployment\"\n    - \"Environment-specific flag states\"\n    - \"User-specific feature access control\"\n    - \"Complete audit trail of flag changes and usage\"\n  \n  implementation_standards:\n    system:\n      rag_engine: true\n      knowledge_graph: true\n      ai_agents: false\n      mobile_access: false\n      home_automation: false\n    \n    security:\n      encryption_at_rest: true\n      encryption_in_transit: true\n      audit_logging: true\n      access_control: true\n    \n    performance:\n      caching: true\n      compression: true\n      load_balancing: true\n      auto_scaling: false\n  \n  management:\n    - \"Centralized configuration - single source of truth\"\n    - \"RESTful API for flag management\"\n    - \"Web UI dashboard for administration\"\n    - \"Git-based configuration tracking\"\n    - \"Instant rollback to previous states\"\n\n# ANONYMOUS AND GENERIC CODE\ncode_standards:\n  anonymization:\n    - \"No personal identifiers in code\"\n    - \"Generic placeholder data for examples\"\n    - \"All external endpoints configurable\"\n    - \"All sensitive data via environment variables\"\n    - \"Zero hardcoded secrets\"\n  \n  implementation_examples:\n    good:\n      description: \"Generic, configurable implementation\"\n      code: |\n        class KnowledgeService:\n            def __init__(self, config: ServiceConfig):\n                self.database_url = config.database_url\n                self.api_key = config.api_key\n                self.endpoint = config.endpoint\n    \n    bad:\n      description: \"Hardcoded, specific implementation\"\n      code: |\n        class KnowledgeService:\n            def __init__(self):\n                self.database_url = \"postgresql://user:pass@localhost:5432/db\"\n                self.api_key = \"sk-1234567890abcdef\"\n  \n  configuration_management:\n    - \"Environment-specific configurations\"\n    - \"Enterprise secret manager integration\"\n    - \"Schema-based configuration validation\"\n    - \"Sensible default values\"\n    - \"Complete configuration documentation\"\n\n# SECURITY STANDARDS\nsecurity:\n  authentication_authorization:\n    - \"Multi-factor authentication for all admin access\"\n    - \"Role-based access control (RBAC)\"\n    - \"Single sign-on (SSO) integration\"\n    - \"Secure session management with timeouts\"\n    - \"JWT or OAuth2 for API authentication\"\n  \n  data_protection:\n    - \"Encryption at rest for all data\"\n    - \"TLS 1.3 for all communications\"\n    - \"Automatic data classification\"\n    - \"Configurable data retention policies\"\n    - \"Data masking in logs and exports\"\n  \n  network_security:\n    - \"Strict firewall rules\"\n    - \"VPN access for remote administration\"\n    - \"Real-time intrusion detection\"\n    - \"Regular vulnerability scanning\"\n    - \"Annual penetration testing\"\n  \n  compliance:\n    - \"GDPR compliance for data privacy\"\n    - \"SOC 2 Type II security controls\"\n    - \"ISO 27001 information security\"\n    - \"HIPAA compliance (if applicable)\"\n    - \"PCI DSS compliance (if applicable)\"\n\n# DEPLOYMENT STANDARDS\ndeployment:\n  infrastructure_as_code:\n    - \"Terraform/CloudFormation for infrastructure\"\n    - \"All infrastructure code in Git\"\n    - \"Identical environments across stages\"\n    - \"Zero manual infrastructure setup\"\n    - \"Instant infrastructure rollback\"\n  \n  container_standards:\n    - \"Multi-stage optimized builds\"\n    - \"Container vulnerability scanning\"\n    - \"Digitally signed images\"\n    - \"CPU and memory limits defined\"\n    - \"Comprehensive health monitoring\"\n  \n  deployment_pipeline:\n    - \"Automated CI/CD integration\"\n    - \"Zero-downtime blue-green deployment\"\n    - \"Gradual canary releases\"\n    - \"Full automated test suite execution\"\n    - \"Post-deployment verification\"\n  \n  monitoring_observability:\n    - \"Centralized aggregated logging\"\n    - \"Performance and business metrics collection\"\n    - \"Proactive alerting system\"\n    - \"Distributed request tracing\"\n    - \"Real-time dashboard visualization\"\n\n# SCALABILITY STANDARDS\nscalability:\n  horizontal_scaling:\n    - \"Stateless application design\"\n    - \"Automatic traffic load balancing\"\n    - \"Dynamic resource auto-scaling\"\n    - \"Horizontal database sharding\"\n    - \"Global CDN integration\"\n  \n  performance_standards:\n    response_time: \"< 200ms for 95% of requests\"\n    throughput: \"Support 10,000+ concurrent users\"\n    availability: \"99.9% uptime SLA\"\n    data_consistency: \"Eventual consistency model\"\n    caching_strategy: \"Multi-layer caching approach\"\n\n# QUALITY ASSURANCE\nquality_assurance:\n  testing_standards:\n    - \"90%+ code coverage required\"\n    - \"End-to-end workflow testing\"\n    - \"Load and stress testing\"\n    - \"Automated security scanning\"\n    - \"Stakeholder acceptance testing\"\n  \n  code_quality:\n    - \"Automated static analysis\"\n    - \"Mandatory peer code review\"\n    - \"Complete API and user documentation\"\n    - \"Comprehensive error handling\"\n    - \"Structured logging throughout\"\n  \n  production_testing:\n    - \"All tests use production data and services\"\n    - \"No skipped or temporary tests\"\n    - \"All test runs logged and auditable\"\n    - \"Real-world user simulation\"\n    - \"Performance benchmarks against production\"\n\n# DISASTER RECOVERY\ndisaster_recovery:\n  backup_strategy:\n    - \"Daily automated backups\"\n    - \"Cross-region geographic redundancy\"\n    - \"Point-in-time recovery capability\"\n    - \"Regular backup restoration testing\"\n    - \"Long-term backup retention\"\n  \n  recovery_procedures:\n    rto_target: \"4-hour recovery time objective\"\n    rpo_target: \"1-hour recovery point objective\"\n    - \"Automated disaster recovery\"\n    - \"Stakeholder notification procedures\"\n    - \"Complete recovery runbooks\"\n    - \"Quarterly disaster recovery drills\"\n\n# COMPLIANCE AND GOVERNANCE\ncompliance_governance:\n  audit_requirements:\n    - \"Complete access audit trail\"\n    - \"All changes tracked and approved\"\n    - \"Complete data flow documentation\"\n    - \"Automated compliance reporting\"\n    - \"Third-party security assessments\"\n  \n  governance_framework:\n    - \"Centralized policy enforcement\"\n    - \"Regular risk evaluation\"\n    - \"Third-party risk assessment\"\n    - \"Formal incident management\"\n    - \"Business continuity planning\"\n\n# IMPLEMENTATION CHECKLISTS\nimplementation_checklists:\n  pre_deployment:\n    - \"Feature flags implemented and tested\"\n    - \"All hardcoded values removed\"\n    - \"Security scanning completed\"\n    - \"Performance testing passed\"\n    - \"Documentation updated\"\n  \n  deployment:\n    - \"Infrastructure provisioned\"\n    - \"Security controls enabled\"\n    - \"Monitoring configured\"\n    - \"Backup systems active\"\n    - \"Disaster recovery tested\"\n  \n  post_deployment:\n    - \"Performance monitoring active\"\n    - \"Security monitoring active\"\n    - \"User training completed\"\n    - \"Support procedures documented\"\n    - \"Maintenance schedule established\"\n\n# MAINTENANCE AND UPDATES\nmaintenance_updates:\n  update_procedures:\n    - \"Zero-downtime updates\"\n    - \"Instant rollback capability\"\n    - \"Full testing before production\"\n    - \"Stakeholder notification\"\n    - \"Post-update validation\"\n  \n  maintenance_windows:\n    - \"Regular scheduled maintenance\"\n    - \"24/7 emergency procedures\"\n    - \"Formal change approval process\"\n    - \"Risk evaluation for all changes\"\n    - \"Stakeholder notification procedures\"\n\n# SUCCESS METRICS\nsuccess_metrics:\n  technical:\n    - \"100% of features configurable via flags\"\n    - \"All tests using production data/services\"\n    - \"Zero critical security vulnerabilities\"\n    - \"99.9% uptime SLA achieved\"\n    - \"All deployments fully automated\"\n  \n  quality:\n    - \"90%+ code coverage maintained\"\n    - \"All tests passing consistently\"\n    - \"Complete documentation coverage\"\n    - \"Zero technical debt\"\n    - \"All compliance requirements met\"\n\n# CONCLUSION\nconclusion: >\n  These enterprise distribution standards ensure the AI-Q Knowledge Library System \n  can be deployed across multiple organizations while maintaining security, scalability, \n  and maintainability. All implementations must adhere to these standards to ensure \n  enterprise-grade quality and compliance. ",
  "conversion_notes": "This file had YAML syntax errors and was converted to basic JSON structure",
  "requires_manual_review": true,
  "extracted_data": {
    "version": "\"1.0\"",
    "last_updated": "\"2025-07-03T00:00:00Z\"",
    "purpose": ">",
    "zero_technical_debt": [
      "\"No TODOs, temporary code, or manual steps allowed\"",
      "\"All code must be production-ready and fully tested\"",
      "\"No commented-out code or debug endpoints\"",
      "\"All changes must be versioned and immutable\""
    ],
    "production_only_testing": [
      "\"All tests must use production data, services, and servers\"",
      "\"No development or test data allowed\"",
      "\"No mock services or simulated environments\"",
      "\"All test runs must be logged and auditable\""
    ],
    "immutable_infrastructure": [
      "\"All infrastructure defined as code\"",
      "\"No manual infrastructure changes\"",
      "\"All environments must be identical\"",
      "\"Instant rollback capability required\""
    ],
    "core_requirements": [
      "\"Zero hardcoded features - all configurable via flags\"",
      "\"Runtime toggle without code deployment\"",
      "\"Environment-specific flag states\"",
      "\"User-specific feature access control\"",
      "\"Complete audit trail of flag changes and usage\""
    ],
    "rag_engine": "true",
    "knowledge_graph": "true",
    "ai_agents": "false",
    "mobile_access": "false",
    "home_automation": "false",
    "encryption_at_rest": "true",
    "encryption_in_transit": "true",
    "audit_logging": "true",
    "access_control": "true",
    "caching": "true",
    "compression": "true",
    "load_balancing": "true",
    "auto_scaling": "false",
    "management": [
      "\"Centralized configuration - single source of truth\"",
      "\"RESTful API for flag management\"",
      "\"Web UI dashboard for administration\"",
      "\"Git-based configuration tracking\"",
      "\"Instant rollback to previous states\""
    ],
    "anonymization": [
      "\"No personal identifiers in code\"",
      "\"Generic placeholder data for examples\"",
      "\"All external endpoints configurable\"",
      "\"All sensitive data via environment variables\"",
      "\"Zero hardcoded secrets\""
    ],
    "description": "\"Hardcoded, specific implementation\"",
    "code": "|",
    "def __init__(self, config": "ServiceConfig):",
    "self.database_url = \"postgresql": "//user:pass@localhost:5432/db\"",
    "configuration_management": [
      "\"Environment-specific configurations\"",
      "\"Enterprise secret manager integration\"",
      "\"Schema-based configuration validation\"",
      "\"Sensible default values\"",
      "\"Complete configuration documentation\""
    ],
    "authentication_authorization": [
      "\"Multi-factor authentication for all admin access\"",
      "\"Role-based access control (RBAC)\"",
      "\"Single sign-on (SSO) integration\"",
      "\"Secure session management with timeouts\"",
      "\"JWT or OAuth2 for API authentication\""
    ],
    "data_protection": [
      "\"Encryption at rest for all data\"",
      "\"TLS 1.3 for all communications\"",
      "\"Automatic data classification\"",
      "\"Configurable data retention policies\"",
      "\"Data masking in logs and exports\""
    ],
    "network_security": [
      "\"Strict firewall rules\"",
      "\"VPN access for remote administration\"",
      "\"Real-time intrusion detection\"",
      "\"Regular vulnerability scanning\"",
      "\"Annual penetration testing\""
    ],
    "compliance": [
      "\"GDPR compliance for data privacy\"",
      "\"SOC 2 Type II security controls\"",
      "\"ISO 27001 information security\"",
      "\"HIPAA compliance (if applicable)\"",
      "\"PCI DSS compliance (if applicable)\""
    ],
    "infrastructure_as_code": [
      "\"Terraform/CloudFormation for infrastructure\"",
      "\"All infrastructure code in Git\"",
      "\"Identical environments across stages\"",
      "\"Zero manual infrastructure setup\"",
      "\"Instant infrastructure rollback\""
    ],
    "container_standards": [
      "\"Multi-stage optimized builds\"",
      "\"Container vulnerability scanning\"",
      "\"Digitally signed images\"",
      "\"CPU and memory limits defined\"",
      "\"Comprehensive health monitoring\""
    ],
    "deployment_pipeline": [
      "\"Automated CI/CD integration\"",
      "\"Zero-downtime blue-green deployment\"",
      "\"Gradual canary releases\"",
      "\"Full automated test suite execution\"",
      "\"Post-deployment verification\""
    ],
    "monitoring_observability": [
      "\"Centralized aggregated logging\"",
      "\"Performance and business metrics collection\"",
      "\"Proactive alerting system\"",
      "\"Distributed request tracing\"",
      "\"Real-time dashboard visualization\""
    ],
    "horizontal_scaling": [
      "\"Stateless application design\"",
      "\"Automatic traffic load balancing\"",
      "\"Dynamic resource auto-scaling\"",
      "\"Horizontal database sharding\"",
      "\"Global CDN integration\""
    ],
    "response_time": "\"< 200ms for 95% of requests\"",
    "throughput": "\"Support 10,000+ concurrent users\"",
    "availability": "\"99.9% uptime SLA\"",
    "data_consistency": "\"Eventual consistency model\"",
    "caching_strategy": "\"Multi-layer caching approach\"",
    "testing_standards": [
      "\"90%+ code coverage required\"",
      "\"End-to-end workflow testing\"",
      "\"Load and stress testing\"",
      "\"Automated security scanning\"",
      "\"Stakeholder acceptance testing\""
    ],
    "code_quality": [
      "\"Automated static analysis\"",
      "\"Mandatory peer code review\"",
      "\"Complete API and user documentation\"",
      "\"Comprehensive error handling\"",
      "\"Structured logging throughout\""
    ],
    "production_testing": [
      "\"All tests use production data and services\"",
      "\"No skipped or temporary tests\"",
      "\"All test runs logged and auditable\"",
      "\"Real-world user simulation\"",
      "\"Performance benchmarks against production\""
    ],
    "backup_strategy": [
      "\"Daily automated backups\"",
      "\"Cross-region geographic redundancy\"",
      "\"Point-in-time recovery capability\"",
      "\"Regular backup restoration testing\"",
      "\"Long-term backup retention\""
    ],
    "rto_target": "\"4-hour recovery time objective\"",
    "rpo_target": "\"1-hour recovery point objective\"",
    "recovery_procedures": [
      "\"Automated disaster recovery\"",
      "\"Stakeholder notification procedures\"",
      "\"Complete recovery runbooks\"",
      "\"Quarterly disaster recovery drills\""
    ],
    "audit_requirements": [
      "\"Complete access audit trail\"",
      "\"All changes tracked and approved\"",
      "\"Complete data flow documentation\"",
      "\"Automated compliance reporting\"",
      "\"Third-party security assessments\""
    ],
    "governance_framework": [
      "\"Centralized policy enforcement\"",
      "\"Regular risk evaluation\"",
      "\"Third-party risk assessment\"",
      "\"Formal incident management\"",
      "\"Business continuity planning\""
    ],
    "pre_deployment": [
      "\"Feature flags implemented and tested\"",
      "\"All hardcoded values removed\"",
      "\"Security scanning completed\"",
      "\"Performance testing passed\"",
      "\"Documentation updated\""
    ],
    "deployment": [
      "\"Infrastructure provisioned\"",
      "\"Security controls enabled\"",
      "\"Monitoring configured\"",
      "\"Backup systems active\"",
      "\"Disaster recovery tested\""
    ],
    "post_deployment": [
      "\"Performance monitoring active\"",
      "\"Security monitoring active\"",
      "\"User training completed\"",
      "\"Support procedures documented\"",
      "\"Maintenance schedule established\""
    ],
    "update_procedures": [
      "\"Zero-downtime updates\"",
      "\"Instant rollback capability\"",
      "\"Full testing before production\"",
      "\"Stakeholder notification\"",
      "\"Post-update validation\""
    ],
    "maintenance_windows": [
      "\"Regular scheduled maintenance\"",
      "\"24/7 emergency procedures\"",
      "\"Formal change approval process\"",
      "\"Risk evaluation for all changes\"",
      "\"Stakeholder notification procedures\""
    ],
    "technical": [
      "\"100% of features configurable via flags\"",
      "\"All tests using production data/services\"",
      "\"Zero critical security vulnerabilities\"",
      "\"99.9% uptime SLA achieved\"",
      "\"All deployments fully automated\""
    ],
    "quality": [
      "\"90%+ code coverage maintained\"",
      "\"All tests passing consistently\"",
      "\"Complete documentation coverage\"",
      "\"Zero technical debt\"",
      "\"All compliance requirements met\""
    ],
    "conclusion": ">"
  }
}